PikaTgBot/__init__.py
PikaTgBot/__main__.py
PikaTgBot/clients/__init__.py
PikaTgBot/core/__init__.py
PikaTgBot/core/database/__init__.py
PikaTgBot/core/database/db_helper.py
PikaTgBot/core/functions/__init__.py
PikaTgBot/core/utilities/__init__.py
PikaTgBot/core/utilities/botutils/__init__.py
PikaTgBot/core/utilities/botutils/assist.py
PikaTgBot/core/utilities/botutils/pluginsdata.py
PikaTgBot/core/utilities/botutils/wrappers.py
PikaTgBot/core/utilities/clientutils/__init__.py
PikaTgBot/core/utilities/clientutils/decorators.py
PikaTgBot/core/utilities/clientutils/load_module.py
PikaTgBot/resources/__init__.py
PikaTgBot/resources/pldata.py
PikaTgBot/resources/reqfxns.py
PikaTgBot/resources/login/__init__.py
PikaTgBot/sysutils/__init__.py
PikaTgBot/sysutils/sysdata/__init__.py
PikaTgBot/sysutils/sysinfo/__init__.py
PikaTgBot-1.4.4.dist-info/LICENSE
PikaTgBot-1.4.4.dist-info/METADATA
PikaTgBot-1.4.4.dist-info/WHEEL
PikaTgBot-1.4.4.dist-info/top_level.txt
PikaTgBot-1.4.4.dist-info/RECORD
